{
  "name": "Larry Davidson",
  "age": 33,
  "address": {
    "street": "Vukmon Pike",
    "city": "Ibsakvew",
    "state": "WA",
    "zip": "94565"
  },
  "contact": {
    "phone": "(381) 551-6503",
    "servicePhone": "800131864"
  },
  "birthday": "1968-11-01T16:19:54.027Z",
  "ip": "2.15.23.210",
  "foo": "bar",
  "profile": {
    "about": "Jo jin uvfa hutfufuw kicigakok ukded lare eju rasjala le zes wattas erofe ila. Tuvusre wocsem zunvucep gi nij ujratod izuacsi cih wanpago ada bezobe tudpuf owi sefzibe efa co iro. Ruvjo ho vericaz pepfepal fe acewod ucgu uhaga kodca vukjoviju bimbovzog ogu duhigha fudukmi ophe metvos nufev tozi.",
    "bio": "Pegoh pes je fok eh ufhoug je agibos mahub ribof meupep kebona ageta pegesbal nufewe amdofu. Mapfa uci tudeti kikiej ganuhod imonewu iju veibi zipmoho uvujo watel ja diftiwwi saulu jimtujuk kamova ka wovbef. Veru kime uzjevga mi urlefige fuludmi da ag ugirezkej foreace onuwo wejuvgab owkar hubvawi."
  },
  "apiKey": "1e982b720cc6badc4df1724b45aa8e6ba495d60a9dd6e9d942af5d780f98f69b",
  "currency": {
    "code": "LTL",
    "name": "Lithuania Litas"
  }
}