{
  "name": "Zachary Guzman",
  "age": 24,
  "address": {
    "street": "Hiwozi Junction",
    "city": "Wusivid",
    "state": "UT",
    "zip": "50237"
  },
  "contact": {
    "phone": "(747) 921-9445",
    "servicePhone": "800614155"
  },
  "birthday": "1962-12-23T20:20:00.065Z",
  "ip": "79.213.113.130",
  "foo": "bar",
  "profile": {
    "about": "Ga piknun kopenomo nem wuwcedmef zapwehro giowifi tibili semivfuh poz soafo da pih jov jemof. Topse jubbo mid lu nik peczacgo rik kurtuve emnoun bu udu bawat dojifrof fif ku eh. Bezisuv vo rumgitife mut tacaw babegbu ziukun wifod mi nar zemweawo naohzus tupab rivfa achawfi. Hijborji temocat depujsek eraupo lahnifa ritezik wukgoku me robocim vu dib mol.",
    "bio": "Liona gotug no lel ogo dini ta lodrulo tezazof ofe muk ibwowik vaksa iwejuv ga purfowib jod garorah. Moj kuljoeh hoz gu wi pu azcab etne ok ujakatbi vi mefavide cisdannoj dubum signi tuwmaone tof. Keewu orulecdo gacof husacwo kabigogi zosuge woczo vunoke oroejuar nicogi teuj sud hikuot. Degalku filharvol coawuwad heldulove wehkiv wizpav fivig dozjen hatwujed niknub rac saris calag jusabeuco cogecibi. Nahgigo wew eco komug rammibok radow evuasi jode kaakesi gemi cen hegoba jub vu caigepa dokno."
  },
  "apiKey": "91ee92e5b86bb37bc7ecfb24ced0faf6c2f8f0e0fa00c0cff6b304ee825b1ee5",
  "currency": {
    "code": "PHP",
    "name": "Philippines Peso"
  }
}