{
  "name": "Jack Obrien",
  "age": 27,
  "address": {
    "street": "Puzga Pass",
    "city": "Pocuvu",
    "state": "MA",
    "zip": "16554"
  },
  "contact": {
    "phone": "(635) 419-3363",
    "servicePhone": "800195687"
  },
  "birthday": "1984-01-10T06:15:21.945Z",
  "ip": "225.136.172.66",
  "foo": "bar",
  "profile": {
    "about": "Us vedosu raflapta lodro lejpi nossapim wupnatsab cecig se dib lu ma ed ad guw. Kigrefab povom suupezi wababte wipo leveb unelo nupa deliiko miuppa midjup zo ja ug wasjiol lokoj loganhas zaruc. Ciramib wowu obmop icezuco kugaw jolalop fadu gic olkabapa hohe liri je vubdej tufosegu dogatogu jefsi. Omnof tivod ja weni gujo muzjo la olizap jigonu cogi gemor apuedico fispaj ka goc owibilfaw zujzad. Ne mokon mi liacavuj lut ran geno onili cuwza opi ti efomo keffomdej aboog.",
    "bio": "Zewa zoko gopwo vejpa agala jakocma dokbe pafeela piv bad lacahut mucu unitijjac. Sifo jeoz tu tadotmo apu tiwege jis dutvi el eprur so memihli hidi zecel tipujpa wahjeul no nuhawa. Lanpuove ruwito noalidu suti ikaso likvace pukabu ige bof gatitwam nowces gonwebo acicicpo weahifib oracbi rowuwpo cesa si."
  },
  "apiKey": "d0a1e3aa3fc41d49531eb9ead9102d633a4edcf5981a149f6d017fda509d3247",
  "currency": {
    "code": "VUV",
    "name": "Vanuatu Vatu"
  }
}