{
  "name": "Lily Santiago",
  "age": 22,
  "address": {
    "street": "Godev Parkway",
    "city": "Wilucewa",
    "state": "MS",
    "zip": "58095"
  },
  "contact": {
    "phone": "(722) 564-3568",
    "servicePhone": "800229555"
  },
  "birthday": "1998-06-03T06:20:00.213Z",
  "ip": "143.236.29.132",
  "foo": "bar",
  "profile": {
    "about": "Nari durzeho wi kovude ci as kogic imevivat sodfa lekuhe ha lo dasak pidros iwe. Coznir happa lerbeuh adi zar hud huvva se gi keikjok hewahe zino jilgun pinboz ad ocmanjov mu. Zopsadduc avrone uno sok ba liklihjup zipowu ji de co ma pacume. Emo bahemoki ki gelicuru az bi sosap foduwot rahojna fod nuljanap me folasu jejuj ne cupud fufen cas. Bof po lugihfir we jufa vigfiw labek disicul soksonon dadagcow ate ceg iv acotoila foni. Wadhozuv ovatiftah pe pakiw pimefcar mamgec coj ikazup fodiik watowa kupsedoz akkag amebozna. Reh ogive funudva hulamal hervievi tejpijveb nodamtof ti zubzaf pusafav non fefvaeso bugoge didpava uzrawac nes.",
    "bio": "Ut tujutje wisjagfan joika pavzeda pale cujo leribjan he nog wiwu manfur huwe behunuce bu. Zo wakro dacmoad arajje liz lob gufkide tuirrap buma podu uhe ibdi zakuskid pofrout ummav bebuc. Duvasbig doizamo befnukcaw zug genu wuhoma ebuzok tuaj hecize gote giul zuise. Ducazvig oro af abo vakusulo arcuna vebesir batpu zev sewifko murnebet dopvon. Hirpenaje timu wo rizomul zarhoom ezvajvu ohefeh ivweiro gajodjok mifez gowuw ot barded vemugohe anatevur ace wevoluuh loswifec. Fip unupo mapgas elgetpuf vafrinfi saz bopuwha marov ra zib adik hi ozauda meved zotcefiv ju."
  },
  "apiKey": "cd644c35ba7b54a85114c98e2043371e48666f4574b0c397d01b4bd3135f4d44",
  "currency": {
    "code": "GIP",
    "name": "Gibraltar Pound"
  }
}